{"lastUsed":1723614191244,"path":"D:\/Back-end 3rd year\/G5 java","projectCount":1,"recentFiles":[{"path":"\/corejava\/src\/practice","parentWorkspace":"D:\/Back-end 3rd year\/G5 java","name":"Employee.java","lastModified":1723434619207,"locationURI":"file:\/D:\/Back-end%203rd%20year\/G5%20java\/corejava\/src\/practice\/Employee.java"},{"path":"\/corejava\/src\/practice","parentWorkspace":"D:\/Back-end 3rd year\/G5 java","name":"Human.java","lastModified":1723434708275,"locationURI":"file:\/D:\/Back-end%203rd%20year\/G5%20java\/corejava\/src\/practice\/Human.java"},{"path":"\/corejava\/src\/packagedemo","parentWorkspace":"D:\/Back-end 3rd year\/G5 java","name":"B.java","lastModified":1723609614078,"locationURI":"file:\/D:\/Back-end%203rd%20year\/G5%20java\/corejava\/src\/packagedemo\/B.java"},{"path":"\/corejava\/src\/packagedemo","parentWorkspace":"D:\/Back-end 3rd year\/G5 java","name":"A.java","lastModified":1723607748093,"locationURI":"file:\/D:\/Back-end%203rd%20year\/G5%20java\/corejava\/src\/packagedemo\/A.java"},{"path":"\/corejava\/src\/staticdemo","parentWorkspace":"D:\/Back-end 3rd year\/G5 java","name":"Student.java","lastModified":1723607330933,"locationURI":"file:\/D:\/Back-end%203rd%20year\/G5%20java\/corejava\/src\/staticdemo\/Student.java"},{"path":"\/corejava\/src\/packagedemo","parentWorkspace":"D:\/Back-end 3rd year\/G5 java","name":"Y.java","lastModified":1723612381831,"locationURI":"file:\/D:\/Back-end%203rd%20year\/G5%20java\/corejava\/src\/packagedemo\/Y.java"},{"path":"\/corejava\/src\/staticdemo","parentWorkspace":"D:\/Back-end 3rd year\/G5 java","name":"Employee.java","lastModified":1723607330933,"locationURI":"file:\/D:\/Back-end%203rd%20year\/G5%20java\/corejava\/src\/staticdemo\/Employee.java"},{"path":"\/corejava\/src\/packagedemo","parentWorkspace":"D:\/Back-end 3rd year\/G5 java","name":"Demo.java","lastModified":1723607330933,"locationURI":"file:\/D:\/Back-end%203rd%20year\/G5%20java\/corejava\/src\/packagedemo\/Demo.java"},{"path":"\/corejava\/src\/inheritencedemo","parentWorkspace":"D:\/Back-end 3rd year\/G5 java","name":"Demo.java","lastModified":1723178769260,"locationURI":"file:\/D:\/Back-end%203rd%20year\/G5%20java\/corejava\/src\/inheritencedemo\/Demo.java"},{"path":"\/corejava\/src\/packagedemo","parentWorkspace":"D:\/Back-end 3rd year\/G5 java","name":"X.java","lastModified":1723612375439,"locationURI":"file:\/D:\/Back-end%203rd%20year\/G5%20java\/corejava\/src\/packagedemo\/X.java"},{"path":"\/corejava\/src\/oopspractice","parentWorkspace":"D:\/Back-end 3rd year\/G5 java","name":"Student.java","lastModified":1723614208498,"locationURI":"file:\/D:\/Back-end%203rd%20year\/G5%20java\/corejava\/src\/oopspractice\/Student.java"},{"path":"\/corejava\/src\/g5class","parentWorkspace":"D:\/Back-end 3rd year\/G5 java","name":"B.java","lastModified":1723175628655,"locationURI":"file:\/D:\/Back-end%203rd%20year\/G5%20java\/corejava\/src\/g5class\/B.java"},{"path":"\/corejava\/src\/practice","parentWorkspace":"D:\/Back-end 3rd year\/G5 java","name":"Demo.java","lastModified":1723437510609,"locationURI":"file:\/D:\/Back-end%203rd%20year\/G5%20java\/corejava\/src\/practice\/Demo.java"},{"path":"\/corejava\/src\/practice","parentWorkspace":"D:\/Back-end 3rd year\/G5 java","name":"Book.java","lastModified":1723434393823,"locationURI":"file:\/D:\/Back-end%203rd%20year\/G5%20java\/corejava\/src\/practice\/Book.java"},{"path":"\/corejava\/src\/practice","parentWorkspace":"D:\/Back-end 3rd year\/G5 java","name":"Y.java","lastModified":1723609630313,"locationURI":"file:\/D:\/Back-end%203rd%20year\/G5%20java\/corejava\/src\/practice\/Y.java"},{"path":"\/corejava\/src\/inheritencedemo","parentWorkspace":"D:\/Back-end 3rd year\/G5 java","name":"Student.java","lastModified":1723177719485,"locationURI":"file:\/D:\/Back-end%203rd%20year\/G5%20java\/corejava\/src\/inheritencedemo\/Student.java"},{"path":"\/corejava\/src\/practice","parentWorkspace":"D:\/Back-end 3rd year\/G5 java","name":"X.java","lastModified":1723608594469,"locationURI":"file:\/D:\/Back-end%203rd%20year\/G5%20java\/corejava\/src\/practice\/X.java"},{"path":"\/corejava\/src\/staticdemo","parentWorkspace":"D:\/Back-end 3rd year\/G5 java","name":"NonStaticDemo.java","lastModified":1723607330933,"locationURI":"file:\/D:\/Back-end%203rd%20year\/G5%20java\/corejava\/src\/staticdemo\/NonStaticDemo.java"},{"path":"\/corejava\/src\/oopspractice","parentWorkspace":"D:\/Back-end 3rd year\/G5 java","name":"Person.java","lastModified":1723612899581,"locationURI":"file:\/D:\/Back-end%203rd%20year\/G5%20java\/corejava\/src\/oopspractice\/Person.java"},{"path":"\/corejava\/src\/practice","parentWorkspace":"D:\/Back-end 3rd year\/G5 java","name":"Student.java","lastModified":1723439817117,"locationURI":"file:\/D:\/Back-end%203rd%20year\/G5%20java\/corejava\/src\/practice\/Student.java"},{"path":"\/corejava\/src\/packagedemo","parentWorkspace":"D:\/Back-end 3rd year\/G5 java","name":"C.java","lastModified":1723608293941,"locationURI":"file:\/D:\/Back-end%203rd%20year\/G5%20java\/corejava\/src\/packagedemo\/C.java"}]}